AAVT/__init__.py
AAVT/blog.py
AAVT/merge.py
AAVT/translate.py
AAVT/whisper_faster.py
AAVT/whisper_openai.py
AAVT/utils/__init__.py
AAVT/utils/srt.py
AAVT-0.8.dist-info/METADATA
AAVT-0.8.dist-info/WHEEL
AAVT-0.8.dist-info/top_level.txt
AAVT-0.8.dist-info/RECORD
