Metadata-Version: 2.1
Name: AAVT
Version: 0.8
Summary: A Python package for Video Translate and Some Tools for Video
Home-page: https://github.com/Chenyme/Chenyme-AAVT
Author: chenyme（Orange橙子）
Author-email: chenyme03@gmail.com
License: UNKNOWN
Platform: UNKNOWN
Classifier: Programming Language :: Python :: 3
Classifier: License :: OSI Approved :: MIT License
Classifier: Operating System :: OS Independent
Requires-Python: >=3.8
Requires-Dist: faster-whisper
Requires-Dist: openai
Requires-Dist: opencv-python
